flask_rich/__init__.py
flask_rich/core.py
flask_rich-0.4.1.dist-info/LICENSE
flask_rich-0.4.1.dist-info/METADATA
flask_rich-0.4.1.dist-info/WHEEL
flask_rich-0.4.1.dist-info/RECORD
