Metadata-Version: 2.1
Name: Flask-Rich
Version: 0.4.1
Summary: Rich implementation for Flask
Home-page: https://github.com/zyf722/Flask-Rich
License: MIT
Keywords: flask,extension,rich
Author: BD103
Author-email: dont@stalk.me
Maintainer: MaxMixAlex
Maintainer-email: MaxMixAlex@protonmail.com
Requires-Python: >=3.8,<4.0
Classifier: Development Status :: 4 - Beta
Classifier: Environment :: Web Environment
Classifier: Intended Audience :: Developers
Classifier: License :: OSI Approved :: MIT License
Classifier: Operating System :: OS Independent
Classifier: Programming Language :: Python
Classifier: Programming Language :: Python :: 3
Classifier: Programming Language :: Python :: 3.8
Classifier: Programming Language :: Python :: 3.9
Classifier: Programming Language :: Python :: 3.10
Classifier: Programming Language :: Python :: 3.11
Classifier: Programming Language :: Python :: 3.12
Requires-Dist: Flask (>=2.3.3)
Requires-Dist: rich (>=13.5.2,<14.0.0)
Requires-Dist: stransi (>=0.3.0,<0.4.0)
Project-URL: Documentation, https://flask-rich.readthedocs.io
Project-URL: Repository, https://github.com/zyf722/Flask-Rich
